tensorfuse_python/__init__.py
tensorfuse_python/constants.py
tensorfuse_python/generic_event_logging.py
tensorfuse_python/openai_event_logging.py
tensorfuse_python/oss_telemtery.py
tensorfuse_python/tensorfuse_python.py
tensorfuse_python/testing/__init__.py
tensorfuse_python/testing/constants.py
tensorfuse_python/testing/preprocessor.py
tensorfuse_python/testing/run_tests.py
tensorfuse_python/testing/testing_utils.py
tensorfuse_python/testing/evaluators/__init__.py
tensorfuse_python/testing/evaluators/evaluator.py
tensorfuse_python/testing/evaluators/evaluator_service.py
tensorfuse_python/testing/evaluators/model_graded_evaluations/__init__.py
tensorfuse_python/testing/evaluators/model_graded_evaluations/model_graded_evaluator.py
tensorfuse_python/testing/generators/__init__.py
tensorfuse_python/testing/generators/prompt_generator.py
tensorfuse_python-0.0.14.dist-info/METADATA
tensorfuse_python-0.0.14.dist-info/WHEEL
tensorfuse_python-0.0.14.dist-info/licenses/LICENSE
tensorfuse_python-0.0.14.dist-info/RECORD
