Metadata-Version: 2.1
Name: tensorfuse_python
Version: 0.0.14
Summary: Python SDK for Tensorfuse
Author-email: Samagra <samagra14@tensorfuse.io>, Divyanshu <dsetia@cs.iitr.ac.in>
License-File: LICENSE
Classifier: License :: OSI Approved :: MIT License
Classifier: Operating System :: OS Independent
Classifier: Programming Language :: Python :: 3
Requires-Python: >=3.7
Requires-Dist: colorama>=0.4.4
Requires-Dist: openai>=0.10.0
Requires-Dist: requests[security]>=2.31.0
